permission_manager/__init__.py
permission_manager/decorators.py
permission_manager/exceptions.py
permission_manager/manager.py
permission_manager/result.py
permission_manager/types.py
permission_manager/utils.py
permission_manager-0.6.1.dist-info/METADATA
permission_manager-0.6.1.dist-info/WHEEL
permission_manager-0.6.1.dist-info/licenses/LICENSE
permission_manager-0.6.1.dist-info/RECORD
