Metadata-Version: 2.4
Name: permission-manager
Version: 0.6.1
Summary: A simple way to manage object permissions.
Project-URL: Homepage, https://github.com/kindlycat/permission-manager
Project-URL: Documentation, https://permission-manager.readthedocs.io
Project-URL: Repository, https://github.com/kindlycat/permission-manager.git
Project-URL: Issues, https://github.com/kindlycat/permission-manager/issues
Author-email: Grigory Mishchenko <grishkokot@gmail.com>
License-Expression: MIT
License-File: LICENSE
Keywords: permissions
Classifier: Development Status :: 5 - Production/Stable
Classifier: License :: OSI Approved :: MIT License
Classifier: Programming Language :: Python :: 3.10
Classifier: Programming Language :: Python :: 3.11
Classifier: Programming Language :: Python :: 3.12
Requires-Python: >=3.10
